Metadata-Version: 2.1
Name: sbmsdp
Version: 0.1
Summary: semi-definite programming for the recovery of stochastic block model
Home-page: https://github.com/zhaofeng-shu33/sbmsdp2
Author: zhaofeng-shu33
Author-email: 616545598@qq.com
Maintainer: zhaofeng-shu33
Maintainer-email: 616545598@qq.com
License: Apache License Version 2.0
Platform: UNKNOWN
Classifier: Development Status :: 4 - Beta
Classifier: Programming Language :: Python :: 3.8
Classifier: Operating System :: OS Independent
